tests/__init__.py
tests/helper.py
tests/test_features.py
tests/test_rest.py
tests/extractor/__init__.py
tests/extractor/test_load_extractor.py
tests/extractor/test_transformations.py
tests/extractor/extraction/__init__.py
tests/extractor/extraction/test_custom_model.py
tests/extractor/extraction/test_model_extractor.py
tests/extractor/extraction/test_pretrained_model.py
tests/extractor/extraction/test_torch_vs_tensorflow.py
tests/model/__init__.py
tests/model/test_load_model.py
tests/model/test_model.py
tests/model/test_transformations.py
tests/model/extraction/__init__.py
tests/model/extraction/test_custom_model.py
tests/model/extraction/test_pretrained_model.py
tests/model/extraction/test_torch_vs_tensorflow.py
thingsvision/__init__.py
thingsvision/_version.py
thingsvision/clip.py
thingsvision/dataloader.py
thingsvision/dataset.py
thingsvision/model.py
thingsvision/model_class.py
thingsvision/simple_tokenizer.py
thingsvision/thingsvision.py
thingsvision/vision.py
thingsvision/core/__init__.py
thingsvision/core/cka/__init__.py
thingsvision/core/cka/base.py
thingsvision/core/cka/cka_base.py
thingsvision/core/cka/cka_numpy.py
thingsvision/core/cka/cka_torch.py
thingsvision/core/cka/helpers.py
thingsvision/core/extraction/__init__.py
thingsvision/core/extraction/base.py
thingsvision/core/extraction/extractor.py
thingsvision/core/extraction/extractors.py
thingsvision/core/extraction/helpers.py
thingsvision/core/extraction/mixin.py
thingsvision/core/extraction/tensorflow.py
thingsvision/core/extraction/torch.py
thingsvision/core/rsa/__init__.py
thingsvision/core/rsa/base.py
thingsvision/core/rsa/helpers.py
thingsvision/cornet/__init__.py
thingsvision/cornet/cornet_r.py
thingsvision/cornet/cornet_rt.py
thingsvision/cornet/cornet_s.py
thingsvision/cornet/cornet_z.py
thingsvision/custom_models/__init__.py
thingsvision/custom_models/alexnet_ecoset.py
thingsvision/custom_models/alexnet_salobjsub.py
thingsvision/custom_models/align.py
thingsvision-2.7.3.dist-info/LICENSE
thingsvision-2.7.3.dist-info/METADATA
thingsvision-2.7.3.dist-info/WHEEL
thingsvision-2.7.3.dist-info/entry_points.txt
thingsvision-2.7.3.dist-info/top_level.txt
thingsvision-2.7.3.dist-info/RECORD
