Metadata-Version: 2.1
Name: thingsvision
Version: 2.7.3
Summary: Extracting image features from state-of-the-art neural networks for Computer Vision made easy
Home-page: https://github.com/ViCCo-Group/thingsvision
Author: Lukas Muttenthaler
Author-email: muttenthaler@cbs.mpg.de
License: MIT License
Keywords: feature extraction
Classifier: Programming Language :: Python :: 3.10
Classifier: Natural Language :: English
Classifier: License :: OSI Approved :: MIT License
Classifier: Operating System :: OS Independent
Requires-Python: >=3.10
License-File: LICENSE
Requires-Dist: ftfy
Requires-Dist: h5py
Requires-Dist: matplotlib
Requires-Dist: numba
Requires-Dist: numpy (<2)
Requires-Dist: open-clip-torch (==3.*)
Requires-Dist: pandas
Requires-Dist: regex
Requires-Dist: safetensors (<0.6)
Requires-Dist: scikit-image
Requires-Dist: scikit-learn
Requires-Dist: scipy
Requires-Dist: tensorflow (<2.16)
Requires-Dist: timm
Requires-Dist: torch (>=2.0.0)
Requires-Dist: torchvision (==0.15.2)
Requires-Dist: torchtyping
Requires-Dist: tqdm
Requires-Dist: accelerate (<1.10.0)
Requires-Dist: transformers (==4.40.1)
Requires-Dist: pytest
